[{"id":"655717f4340d2ac9","type":"tab","label":"Patient calls for help","disabled":false,"info":"","env":[]},{"id":"3c0e7c79b4495502","type":"ibmiot in","z":"655717f4340d2ac9","authentication":"apiKey","apiKey":"5a7690d8a395090e","inputType":"evt","logicalInterface":"","ruleId":"","deviceId":"","applicationId":"","deviceType":"+","eventType":"+","commandType":"","format":"json","name":"upload help button data from mkr1010","service":"registered","allDevices":true,"allApplications":"","allDeviceTypes":true,"allLogicalInterfaces":"","allEvents":true,"allCommands":"","allFormats":"","qos":0,"x":270,"y":360,"wires":[["adabe13032f1bbe1"]]},{"id":"adabe13032f1bbe1","type":"change","z":"655717f4340d2ac9","name":"alarm type 4","rules":[{"t":"set","p":"payload","pt":"msg","to":"{\"alarm\": 4}","tot":"jsonata"}],"action":"","property":"","from":"","to":"","reg":false,"x":510,"y":360,"wires":[["a6d7bb4f9f120ee5"]]},{"id":"a6d7bb4f9f120ee5","type":"change","z":"655717f4340d2ac9","name":"","rules":[{"t":"set","p":"topic","pt":"msg","to":"\"iot-2/type/mkr1010/id/4c11ae916fb0/cmd/alarm/fmt/json\"\t\t","tot":"jsonata"}],"action":"","property":"","from":"","to":"","reg":false,"x":700,"y":360,"wires":[["62c1a8eafedded43","baffe1df0a675dd0","600d77434c27d964"]]},{"id":"62c1a8eafedded43","type":"mqtt out","z":"655717f4340d2ac9","name":"Return to Xingyu's mkr1010","topic":"","qos":"0","retain":"","respTopic":"","contentType":"","userProps":"","correl":"","expiry":"","broker":"74c90b6a43c02ca8","x":960,"y":360,"wires":[]},{"id":"600d77434c27d964","type":"change","z":"655717f4340d2ac9","name":"SMS setting","rules":[{"t":"set","p":"topic","pt":"msg","to":"IMPORTANT! Patient Call for Help!!!","tot":"str"},{"t":"set","p":"payload","pt":"msg","to":"The patient has an emergency and is calling for help, please help him in time!!!","tot":"str"}],"action":"","property":"","from":"","to":"","reg":false,"x":910,"y":480,"wires":[["7f1aa2982c665861"]]},{"id":"baffe1df0a675dd0","type":"change","z":"655717f4340d2ac9","name":"email setting","rules":[{"t":"set","p":"topic","pt":"msg","to":"IMPORTANT! Patient Call for Help!!!","tot":"str"},{"t":"set","p":"payload","pt":"msg","to":"The patient has an emergency and is calling for help, please help him in time!!!","tot":"str"}],"action":"","property":"","from":"","to":"","reg":false,"x":910,"y":420,"wires":[["a2224bf4a76c14e9"]]},{"id":"a2224bf4a76c14e9","type":"e-mail","z":"655717f4340d2ac9","server":"smtp.qq.com","port":"587","secure":false,"tls":false,"name":"zczlx79@ucl.ac.uk","dname":"roommate and healthcare center","x":1130,"y":420,"wires":[]},{"id":"7f1aa2982c665861","type":"twilio out","z":"655717f4340d2ac9","twilio":"19229f00d2d94efa","twilioType":"sms","url":"","number":"+447536341037","name":"roommate and healthcare center","x":1130,"y":480,"wires":[]},{"id":"5a7690d8a395090e","type":"ibmiot","name":"Jinyang's 1010","keepalive":"60","serverName":"ts9xp8.messaging.internetofthings.ibmcloud.com","cleansession":true,"appId":"","shared":false},{"id":"74c90b6a43c02ca8","type":"mqtt-broker","name":"","broker":"dva68t.messaging.internetofthings.ibmcloud.com","port":"1883","clientid":"a:dva68t:mqtttest","autoConnect":true,"usetls":false,"protocolVersion":"4","keepalive":"60","cleansession":true,"birthTopic":"","birthQos":"0","birthPayload":"","birthMsg":{},"closeTopic":"","closeQos":"0","closePayload":"","closeMsg":{},"willTopic":"","willQos":"0","willPayload":"","willMsg":{},"sessionExpiry":""},{"id":"19229f00d2d94efa","type":"twilio-api","name":"+19378723161","sid":"ACb7b88c92ff39cde364760d089ba1479a","from":"+19378723161"}]